django_admin_better_image
